{"skeleton":{"hash":"ASCh5Z4DVk8eYcuf9JedwESAHcU","spine":"3.8.99","x":-119.15,"y":-113.33,"width":247.04,"height":226.77,"images":"./images/","audio":"D:/新建文件夹/文件2/slot项目/20230317小恶魔   6h1/wild2"},"bones":[{"name":"root"},{"name":"bone","parent":"root","scaleX":0.1347,"scaleY":0.1347},{"name":"bone2","parent":"bone","x":-495.65,"y":-4.18,"color":"ffffffff"},{"name":"bone3","parent":"bone","x":-152.54,"y":7.25,"color":"ffffffff"},{"name":"bone4","parent":"bone","x":0.71,"y":-1.9,"color":"ffffffff"},{"name":"bone5","parent":"bone","x":508.51,"y":9.54,"color":"ffffffff"},{"name":"bone6","parent":"root","scaleX":0.1347,"scaleY":0.1347},{"name":"bone7","parent":"bone","x":7.95,"y":115.71},{"name":"bone8","parent":"bone","x":-731.1,"y":-129.05,"scaleX":1.6169,"scaleY":1.6169},{"name":"bone9","parent":"bone","x":-327.45,"y":-129.05,"scaleX":1.6169,"scaleY":1.6169},{"name":"bone10","parent":"bone","x":-27.06,"y":-129.05,"scaleX":1.6169,"scaleY":1.6169},{"name":"bone11","parent":"bone","x":219.35,"y":-129.05,"scaleX":1.6169,"scaleY":1.6169},{"name":"bone12","parent":"bone","rotation":1.98,"x":20.55,"y":-581.93,"scaleX":5.8414,"scaleY":5.8414}],"slots":[{"name":"root","bone":"root","attachment":"root"},{"name":"ban2","bone":"bone6","attachment":"ban"},{"name":"ban","bone":"bone7","attachment":"ban"},{"name":"bone7","bone":"bone7","attachment":"bone7"},{"name":"ban4","bone":"bone7","attachment":"ban3"},{"name":"ban3","bone":"bone7","attachment":"ban2","blend":"additive"},{"name":"tx02","bone":"bone8","attachment":"tx09","blend":"additive"},{"name":"tx2","bone":"bone9","attachment":"tx09","blend":"additive"},{"name":"tx3","bone":"bone10","attachment":"tx09","blend":"additive"},{"name":"tx4","bone":"bone11","attachment":"tx09","blend":"additive"},{"name":"d","bone":"bone5","attachment":"d"},{"name":"d2","bone":"bone5","attachment":"d gg","blend":"additive"},{"name":"l2","bone":"bone4","attachment":"l"},{"name":"l3","bone":"bone4","attachment":"l gg","blend":"additive"},{"name":"i","bone":"bone3","attachment":"i"},{"name":"i2","bone":"bone3","attachment":"i gg","blend":"additive"},{"name":"w","bone":"bone2","attachment":"w"},{"name":"w2","bone":"bone2","attachment":"w gg","blend":"additive"},{"name":"txs0","bone":"bone12","color":"ffb085ff","attachment":"txs00","blend":"additive"},{"name":"txs1","bone":"bone12","color":"ffb085ff","attachment":"txs00","blend":"additive"},{"name":"kuang","bone":"root"}],"skins":[{"name":"default","attachments":{"ban":{"ban":{"type":"mesh","uvs":[0.99628,1,0.00372,1,0.00372,0,0.99628,0],"triangles":[1,2,3,1,3,0],"vertices":[733.55,-958.71,-734.45,-958.71,-734.45,729.29,733.55,729.29],"hull":4,"edges":[0,2,2,4,4,6,0,6],"width":1479,"height":1686}},"ban2":{"ban":{"type":"mesh","uvs":[0.99628,1,0.00372,1,0.00372,0,0.99628,0],"triangles":[1,2,3,1,3,0],"vertices":[741.5,-843,-726.5,-843,-726.5,845,741.5,845],"hull":4,"edges":[0,2,2,4,4,6,0,6],"width":1479,"height":1686}},"ban3":{"ban2":{"x":2.54,"y":-57.41,"width":1462,"height":1431}},"ban4":{"ban3":{"type":"mesh","uvs":[0.06917,0.87705,0.0332,0.83807,0.03978,0.14335,0.05619,0.1045,0.93919,0.10051,0.95696,0.13821,0.95363,0.84479,0.91358,0.87839],"triangles":[2,3,4,2,4,5,6,2,5,1,2,6,7,0,1,6,7,1],"vertices":[-637.65,-751.17,-690.84,-685.38,-681.11,487.32,-656.85,552.89,649.12,559.63,675.4,495.99,670.47,-696.72,611.24,-753.43],"hull":8,"edges":[6,8,8,10,10,12,12,14,14,0,0,2,2,4,4,6,4,10,2,12],"width":1479,"height":1686}},"bone7":{"bone7":{"type":"clipping","end":"ban3","vertexCount":45,"vertices":[-636.24,189.24,-666.1,-33.68,-686,-495.43,-590.47,-324.26,-556.63,-439.7,-518.88,-677.76,-472.13,-337.8,-385.68,-531.64,-320.77,-338.9,-272.01,-441.69,-244.15,-332.22,-154.13,-583.75,-133.26,-476.63,-119.96,-408.32,-46.74,-338.12,19.19,-474.58,128.04,-326.25,230.39,-520.86,335.03,-342.17,375.94,-437.53,415.73,-205.86,473.75,-256.16,567.48,-390.57,633.58,-511.35,625.62,501.72,559.12,376.5,456.96,268.92,384.01,561.01,362.46,392.18,256.19,274.66,187.53,347.62,173.91,457.36,98.61,344.5,56.76,286.5,-2.77,347.55,-27.79,419.85,-101.7,480.1,-187.04,397.52,-266.35,325.86,-352.97,366.42,-382.5,524.62,-448.25,360.41,-496.71,445.17,-584.54,344.27,-633.58,303.73],"color":"ce3a3aff"}},"d":{"d":{"type":"mesh","uvs":[1,0.73583,0,0.73583,0,0,1,0],"triangles":[2,3,0,1,2,0],"vertices":[231.99,-279.11,-222.01,-279.11,-222.01,262.46,231.99,262.46],"hull":4,"edges":[0,2,2,4,4,6,0,6],"width":454,"height":736}},"d2":{"d gg":{"type":"mesh","uvs":[1,1,0,1,0,0,1,0],"triangles":[1,2,3,1,3,0],"vertices":[254.8,-298.99,-348.2,-298.99,-348.2,300.01,254.8,300.01],"hull":4,"edges":[0,2,2,4,4,6,0,6],"width":100,"height":99}},"i":{"i":{"type":"mesh","uvs":[1,1,0,1,0,0,1,0],"triangles":[1,2,3,1,3,0],"vertices":[96.04,-296.25,-105.96,-296.25,-105.96,291.75,96.04,291.75],"hull":4,"edges":[0,2,2,4,4,6,0,6],"width":202,"height":588}},"i2":{"i gg":{"type":"mesh","uvs":[1,1,0,1,0,0,1,0],"triangles":[1,2,3,1,3,0],"vertices":[123.77,-369.78,-180.23,-369.78,-180.23,340.22,123.77,340.22],"hull":4,"edges":[0,2,2,4,4,6,0,6],"width":100,"height":234}},"l2":{"l":{"type":"mesh","uvs":[1,0.77186,0,0.77186,0,0,1,0],"triangles":[2,3,0,1,2,0],"vertices":[344.79,-288.26,-64.21,-288.26,-64.21,299.9,344.79,299.9],"hull":4,"edges":[0,2,2,4,4,6,0,6],"width":409,"height":762}},"l3":{"l gg":{"type":"mesh","uvs":[1,1,0,1,0,0,1,0],"triangles":[1,2,3,1,3,0],"vertices":[413.84,-340.2,-102.16,-340.2,-102.16,351.8,413.84,351.8],"hull":4,"edges":[0,2,2,4,4,6,0,6],"width":100,"height":134}},"root":{"root":{"type":"clipping","end":"ban","vertexCount":6,"vertices":[-97.17,112.94,-96.77,113.42,99.14,113.45,99.44,113.03,99.3,-113.33,-96.97,-113.28],"color":"ce3a3aff"}},"tx02":{"tx02":{"x":201.75,"width":500,"height":500},"tx03":{"x":201.75,"width":500,"height":500},"tx04":{"x":201.75,"width":500,"height":500},"tx05":{"x":201.75,"width":500,"height":500},"tx06":{"x":201.75,"width":500,"height":500},"tx07":{"x":201.75,"width":500,"height":500},"tx08":{"x":201.75,"width":500,"height":500},"tx09":{"x":201.75,"width":500,"height":500},"tx10":{"x":201.75,"width":500,"height":500},"tx11":{"x":201.75,"width":500,"height":500},"tx12":{"x":201.75,"width":500,"height":500},"tx13":{"x":201.75,"width":500,"height":500},"tx14":{"x":201.75,"width":500,"height":500},"tx15":{"x":201.75,"width":500,"height":500},"tx16":{"x":201.75,"width":500,"height":500},"tx17":{"x":201.75,"width":500,"height":500},"tx18":{"x":201.75,"width":500,"height":500},"tx19":{"x":201.75,"width":500,"height":500},"tx20":{"x":201.75,"width":500,"height":500},"tx21":{"x":201.75,"width":500,"height":500},"tx22":{"x":201.75,"width":500,"height":500}},"tx2":{"tx02":{"x":201.75,"width":500,"height":500},"tx03":{"x":201.75,"width":500,"height":500},"tx04":{"x":201.75,"width":500,"height":500},"tx05":{"x":201.75,"width":500,"height":500},"tx06":{"x":201.75,"width":500,"height":500},"tx07":{"x":201.75,"width":500,"height":500},"tx08":{"x":201.75,"width":500,"height":500},"tx09":{"x":201.75,"width":500,"height":500},"tx10":{"x":201.75,"width":500,"height":500},"tx11":{"x":201.75,"width":500,"height":500},"tx12":{"x":201.75,"width":500,"height":500},"tx13":{"x":201.75,"width":500,"height":500},"tx14":{"x":201.75,"width":500,"height":500},"tx15":{"x":201.75,"width":500,"height":500},"tx16":{"x":201.75,"width":500,"height":500},"tx17":{"x":201.75,"width":500,"height":500},"tx18":{"x":201.75,"width":500,"height":500},"tx19":{"x":201.75,"width":500,"height":500},"tx20":{"x":201.75,"width":500,"height":500},"tx21":{"x":201.75,"width":500,"height":500},"tx22":{"x":201.75,"width":500,"height":500}},"tx3":{"tx02":{"x":201.75,"width":500,"height":500},"tx03":{"x":201.75,"width":500,"height":500},"tx04":{"x":201.75,"width":500,"height":500},"tx05":{"x":201.75,"width":500,"height":500},"tx06":{"x":201.75,"width":500,"height":500},"tx07":{"x":201.75,"width":500,"height":500},"tx08":{"x":201.75,"width":500,"height":500},"tx09":{"x":201.75,"width":500,"height":500},"tx10":{"x":201.75,"width":500,"height":500},"tx11":{"x":201.75,"width":500,"height":500},"tx12":{"x":201.75,"width":500,"height":500},"tx13":{"x":201.75,"width":500,"height":500},"tx14":{"x":201.75,"width":500,"height":500},"tx15":{"x":201.75,"width":500,"height":500},"tx16":{"x":201.75,"width":500,"height":500},"tx17":{"x":201.75,"width":500,"height":500},"tx18":{"x":201.75,"width":500,"height":500},"tx19":{"x":201.75,"width":500,"height":500},"tx20":{"x":201.75,"width":500,"height":500},"tx21":{"x":201.75,"width":500,"height":500},"tx22":{"x":201.75,"width":500,"height":500}},"tx4":{"tx02":{"x":201.75,"width":500,"height":500},"tx03":{"x":201.75,"width":500,"height":500},"tx04":{"x":201.75,"width":500,"height":500},"tx05":{"x":201.75,"width":500,"height":500},"tx06":{"x":201.75,"width":500,"height":500},"tx07":{"x":201.75,"width":500,"height":500},"tx08":{"x":201.75,"width":500,"height":500},"tx09":{"x":201.75,"width":500,"height":500},"tx10":{"x":201.75,"width":500,"height":500},"tx11":{"x":201.75,"width":500,"height":500},"tx12":{"x":201.75,"width":500,"height":500},"tx13":{"x":201.75,"width":500,"height":500},"tx14":{"x":201.75,"width":500,"height":500},"tx15":{"x":201.75,"width":500,"height":500},"tx16":{"x":201.75,"width":500,"height":500},"tx17":{"x":201.75,"width":500,"height":500},"tx18":{"x":201.75,"width":500,"height":500},"tx19":{"x":201.75,"width":500,"height":500},"tx20":{"x":201.75,"width":500,"height":500},"tx21":{"x":201.75,"width":500,"height":500},"tx22":{"x":201.75,"width":500,"height":500}},"txs0":{"txs00":{"y":77.94,"width":260,"height":191},"txs01":{"y":77.71,"width":260,"height":191},"txs02":{"y":77.71,"width":260,"height":191},"txs03":{"y":77.71,"width":260,"height":191},"txs04":{"y":77.71,"width":260,"height":191},"txs05":{"y":77.71,"width":260,"height":191},"txs06":{"y":77.71,"width":260,"height":191},"txs07":{"y":77.71,"width":260,"height":191},"txs08":{"y":77.71,"width":260,"height":191},"txs09":{"y":77.71,"width":260,"height":191},"txs10":{"y":77.71,"width":260,"height":191},"txs11":{"y":77.71,"width":260,"height":191},"txs12":{"y":77.71,"width":260,"height":191},"txs13":{"y":77.71,"width":260,"height":191},"txs14":{"y":77.71,"width":260,"height":191},"txs15":{"y":77.71,"width":260,"height":191},"txs16":{"y":77.71,"width":260,"height":191},"txs17":{"y":77.71,"width":260,"height":191},"txs18":{"y":77.71,"width":260,"height":191},"txs19":{"y":77.71,"width":260,"height":191},"txs20":{"y":77.71,"width":260,"height":191},"txs21":{"y":77.71,"width":260,"height":191}},"txs1":{"txs00":{"y":77.94,"width":260,"height":191},"txs01":{"y":77.71,"width":260,"height":191},"txs02":{"y":77.71,"width":260,"height":191},"txs03":{"y":77.71,"width":260,"height":191},"txs04":{"y":77.71,"width":260,"height":191},"txs05":{"y":77.71,"width":260,"height":191},"txs06":{"y":77.71,"width":260,"height":191},"txs07":{"y":77.71,"width":260,"height":191},"txs08":{"y":77.71,"width":260,"height":191},"txs09":{"y":77.71,"width":260,"height":191},"txs10":{"y":77.71,"width":260,"height":191},"txs11":{"y":77.71,"width":260,"height":191},"txs12":{"y":77.71,"width":260,"height":191},"txs13":{"y":77.71,"width":260,"height":191},"txs14":{"y":77.71,"width":260,"height":191},"txs15":{"y":77.71,"width":260,"height":191},"txs16":{"y":77.71,"width":260,"height":191},"txs17":{"y":77.71,"width":260,"height":191},"txs18":{"y":77.71,"width":260,"height":191},"txs19":{"y":77.71,"width":260,"height":191},"txs20":{"y":77.71,"width":260,"height":191},"txs21":{"y":77.71,"width":260,"height":191}},"w":{"w":{"type":"mesh","uvs":[1,1,0,1,0,0,1,0],"triangles":[1,2,3,1,3,0],"vertices":[240.15,-278.82,-243.85,-278.82,-243.85,290.18,240.15,290.18],"hull":4,"edges":[0,2,2,4,4,6,0,6],"width":484,"height":569}},"w2":{"w gg":{"type":"mesh","uvs":[1,1,0,1,0,0,1,0],"triangles":[1,2,3,1,3,0],"vertices":[259.78,-561.88,-389.22,-561.88,-389.22,455.12,259.78,455.12],"hull":4,"edges":[0,2,2,4,4,6,0,6],"width":100,"height":157}}}}],"animations":{"win":{"slots":{"ban3":{"color":[{"color":"ffffff00","curve":0.253,"c3":0.622,"c4":0.48},{"time":0.3,"color":"fffa8cff","curve":0.334,"c2":0.33,"c3":0.67,"c4":0.68},{"time":0.7333,"color":"ffffffee","curve":0.381,"c2":0.55,"c3":0.742},{"time":1.6667,"color":"ffffff00"}]},"d2":{"color":[{"color":"ffffff00","curve":"stepped"},{"time":0.1,"color":"ffffff00","curve":0.312,"c2":0.22,"c3":0.647,"c4":0.56},{"time":0.3667,"color":"ffef82ff","curve":"stepped"},{"time":0.5,"color":"ffef82ff","curve":0.324,"c2":0.3,"c3":0.658,"c4":0.63},{"time":0.7667,"color":"ffffff00"}]},"i2":{"color":[{"color":"ffffff00","curve":"stepped"},{"time":0.1667,"color":"ffffff00","curve":0.31,"c3":0.645,"c4":0.35},{"time":0.2667,"color":"ffef82ff","curve":"stepped"},{"time":0.3333,"color":"ffef82ff","curve":0.324,"c2":0.3,"c3":0.658,"c4":0.63},{"time":0.6,"color":"ffffff00"}]},"l3":{"color":[{"color":"ffffff00","curve":"stepped"},{"time":0.2333,"color":"ffffff00","curve":0.312,"c2":0.22,"c3":0.647,"c4":0.56},{"time":0.3,"color":"ffef82ff","curve":"stepped"},{"time":0.4333,"color":"ffef82ff","curve":0.324,"c2":0.3,"c3":0.658,"c4":0.63},{"time":0.7,"color":"ffffff00"}]},"tx02":{"attachment":[{"name":null},{"time":0.2333,"name":"tx03"},{"time":0.2667,"name":"tx05"},{"time":0.3,"name":"tx07"},{"time":0.3333,"name":"tx09"},{"time":0.3667,"name":"tx11"},{"time":0.4,"name":"tx13"},{"time":0.4333,"name":"tx15"},{"time":0.4667,"name":"tx17"},{"time":0.5,"name":"tx19"},{"time":0.5333,"name":"tx21"},{"time":0.5667,"name":null}]},"tx2":{"attachment":[{"name":null},{"time":0.3333,"name":"tx03"},{"time":0.3667,"name":"tx05"},{"time":0.4,"name":"tx07"},{"time":0.4333,"name":"tx09"},{"time":0.4667,"name":"tx11"},{"time":0.5,"name":"tx13"},{"time":0.5333,"name":"tx15"},{"time":0.5667,"name":"tx17"},{"time":0.6,"name":"tx19"},{"time":0.6333,"name":"tx21"},{"time":0.6667,"name":null}]},"tx3":{"attachment":[{"name":null},{"time":0.4333,"name":"tx03"},{"time":0.4667,"name":"tx05"},{"time":0.5,"name":"tx07"},{"time":0.5333,"name":"tx09"},{"time":0.5667,"name":"tx11"},{"time":0.6,"name":"tx13"},{"time":0.6333,"name":"tx15"},{"time":0.6667,"name":"tx17"},{"time":0.7,"name":"tx19"},{"time":0.7333,"name":"tx21"},{"time":0.7667,"name":null}]},"tx4":{"attachment":[{"name":null},{"time":0.5,"name":"tx03"},{"time":0.5333,"name":"tx04"},{"time":0.5667,"name":"tx05"},{"time":0.6,"name":"tx06"},{"time":0.6333,"name":"tx07"},{"time":0.6667,"name":"tx08"},{"time":0.7,"name":"tx09"},{"time":0.7333,"name":"tx10"},{"time":0.7667,"name":"tx11"},{"time":0.8,"name":"tx12"},{"time":0.8333,"name":"tx13"},{"time":0.8667,"name":"tx14"},{"time":0.9,"name":"tx15"},{"time":0.9333,"name":"tx16"},{"time":0.9667,"name":"tx17"},{"time":1,"name":"tx18"},{"time":1.0333,"name":"tx19"},{"time":1.0667,"name":"tx20"},{"time":1.1,"name":"tx21"},{"time":1.1333,"name":"tx22"},{"time":1.1667,"name":null}]},"txs0":{"color":[{"color":"ffb08500","curve":0.25,"c3":0.75},{"time":0.3333,"color":"ffb085ff","curve":0.276,"c3":0.621,"c4":0.4},{"time":0.5,"color":"ffb085ce","curve":0.333,"c2":0.33,"c3":0.758},{"time":1,"color":"ffb085c1","curve":0.25,"c3":0.75},{"time":1.6667,"color":"ffb085ff"}],"attachment":[{"time":0.0333,"name":"txs01"},{"time":0.0667,"name":"txs02"},{"time":0.1,"name":"txs03"},{"time":0.1667,"name":"txs04"},{"time":0.2,"name":"txs05"},{"time":0.2333,"name":"txs06"},{"time":0.2667,"name":"txs07"},{"time":0.3,"name":"txs08"},{"time":0.3333,"name":"txs09"},{"time":0.3667,"name":"txs10"},{"time":0.4333,"name":"txs11"},{"time":0.4667,"name":"txs12"},{"time":0.5,"name":"txs13"},{"time":0.5667,"name":"txs14"},{"time":0.6,"name":"txs15"},{"time":0.6333,"name":"txs16"},{"time":0.6667,"name":"txs17"},{"time":0.7,"name":"txs18"},{"time":0.7667,"name":"txs19"},{"time":0.8,"name":"txs20"},{"time":0.8333,"name":"txs21"},{"time":0.8667,"name":"txs00"},{"time":0.9,"name":"txs01"},{"time":0.9333,"name":"txs02"},{"time":0.9667,"name":"txs03"},{"time":1,"name":"txs04"},{"time":1.0667,"name":"txs05"},{"time":1.1,"name":"txs06"},{"time":1.1333,"name":"txs07"},{"time":1.1667,"name":"txs08"},{"time":1.2,"name":"txs09"},{"time":1.2333,"name":"txs10"},{"time":1.3,"name":"txs11"},{"time":1.3333,"name":"txs12"},{"time":1.3667,"name":"txs13"},{"time":1.4,"name":"txs14"},{"time":1.4333,"name":"txs15"},{"time":1.4667,"name":"txs16"},{"time":1.5,"name":"txs17"},{"time":1.5333,"name":"txs18"},{"time":1.5667,"name":"txs19"},{"time":1.6,"name":"txs20"},{"time":1.6333,"name":"txs21"},{"time":1.6667,"name":"txs00"}]},"txs1":{"color":[{"color":"ffb08500","curve":0.25,"c3":0.75},{"time":0.3333,"color":"ffb085ff","curve":0.276,"c3":0.621,"c4":0.4},{"time":0.5,"color":"ffb085ce","curve":0.333,"c2":0.33,"c3":0.758},{"time":1,"color":"ffb085c1","curve":0.25,"c3":0.75},{"time":1.6667,"color":"ffb085ff"}],"attachment":[{"time":0.0333,"name":"txs01"},{"time":0.0667,"name":"txs02"},{"time":0.1,"name":"txs03"},{"time":0.1667,"name":"txs04"},{"time":0.2,"name":"txs05"},{"time":0.2333,"name":"txs06"},{"time":0.2667,"name":"txs07"},{"time":0.3,"name":"txs08"},{"time":0.3333,"name":"txs09"},{"time":0.3667,"name":"txs10"},{"time":0.4333,"name":"txs11"},{"time":0.4667,"name":"txs12"},{"time":0.5,"name":"txs13"},{"time":0.5667,"name":"txs14"},{"time":0.6,"name":"txs15"},{"time":0.6333,"name":"txs16"},{"time":0.6667,"name":"txs17"},{"time":0.7,"name":"txs18"},{"time":0.7667,"name":"txs19"},{"time":0.8,"name":"txs20"},{"time":0.8333,"name":"txs21"},{"time":0.8667,"name":"txs00"},{"time":0.9,"name":"txs01"},{"time":0.9333,"name":"txs02"},{"time":0.9667,"name":"txs03"},{"time":1,"name":"txs04"},{"time":1.0667,"name":"txs05"},{"time":1.1,"name":"txs06"},{"time":1.1333,"name":"txs07"},{"time":1.1667,"name":"txs08"},{"time":1.2,"name":"txs09"},{"time":1.2333,"name":"txs10"},{"time":1.3,"name":"txs11"},{"time":1.3333,"name":"txs12"},{"time":1.3667,"name":"txs13"},{"time":1.4,"name":"txs14"},{"time":1.4333,"name":"txs15"},{"time":1.4667,"name":"txs16"},{"time":1.5,"name":"txs17"},{"time":1.5333,"name":"txs18"},{"time":1.5667,"name":"txs19"},{"time":1.6,"name":"txs20"},{"time":1.6333,"name":"txs21"},{"time":1.6667,"name":"txs00"}]},"w2":{"color":[{"color":"ffffff00","curve":"stepped"},{"time":0.1,"color":"ffffff00","curve":0.312,"c2":0.22,"c3":0.647,"c4":0.56},{"time":0.1667,"color":"ffef82ff","curve":"stepped"},{"time":0.2667,"color":"ffef82ff","curve":0.324,"c2":0.3,"c3":0.658,"c4":0.63},{"time":0.5,"color":"ffffff00"}]}},"bones":{"bone7":{"scale":[{"time":0.3,"curve":0.329,"c2":0.32,"c3":0.662,"c4":0.65},{"time":0.3667,"x":0.981,"y":0.981,"curve":0.323,"c2":0.3,"c3":0.659,"c4":0.64},{"time":0.4333,"curve":0.329,"c2":0.32,"c3":0.662,"c4":0.65},{"time":0.5,"x":0.981,"y":0.981,"curve":0.323,"c2":0.3,"c3":0.659,"c4":0.64},{"time":0.5667,"curve":0.329,"c2":0.32,"c3":0.662,"c4":0.65},{"time":0.6333,"x":0.981,"y":0.981,"curve":0.323,"c2":0.3,"c3":0.659,"c4":0.64},{"time":0.7,"curve":"stepped"},{"time":0.7667,"curve":0.329,"c2":0.32,"c3":0.662,"c4":0.65},{"time":0.8333,"x":0.981,"y":0.981,"curve":0.323,"c2":0.3,"c3":0.659,"c4":0.64},{"time":0.9}]},"bone12":{"rotate":[{"angle":2.59}],"translate":[{"y":8.2,"curve":0.25,"c3":0.75},{"time":0.1667,"y":31.64,"curve":"stepped"},{"time":1,"y":31.64,"curve":0.25,"c3":0.75},{"time":1.6667,"y":8.2}],"scale":[{"y":1.553,"curve":0.25,"c3":0.75},{"time":0.1667,"y":1.106,"curve":"stepped"},{"time":0.5,"y":1.106,"curve":0.37,"c2":0.48,"c3":0.753},{"time":1,"y":2.004,"curve":0.25,"c3":0.75},{"time":1.6667,"y":1.553}]},"bone5":{"translate":[{"curve":0.31,"c3":0.645,"c4":0.35},{"time":0.1,"x":-95.54,"curve":0.316,"c2":0.23,"c3":0.651,"c4":0.57},{"time":0.2333,"x":61.64,"curve":"stepped"},{"time":0.4333,"x":61.64,"curve":0.302,"c2":0.22,"c3":0.646,"c4":0.59},{"time":0.5}],"scale":[{"curve":0.305,"c3":0.64,"c4":0.36},{"time":0.1,"x":0.448,"y":0.448,"curve":0.314,"c2":0.24,"c3":0.649,"c4":0.58},{"time":0.2333,"x":1.14,"y":1.14,"curve":0.32,"c2":0.29,"c3":0.757},{"time":0.4333,"x":1.875,"y":1.875,"curve":0.32,"c2":0.29,"c3":0.757},{"time":0.5,"curve":0.331,"c3":0.665,"c4":0.33},{"time":0.5667,"x":1.023,"y":1.023,"curve":0.307,"c2":0.04,"c3":0.642,"c4":0.4},{"time":0.6333,"x":0.983,"y":0.983,"curve":0.331,"c3":0.665,"c4":0.33},{"time":0.7,"x":1.023,"y":1.023,"curve":0.307,"c2":0.04,"c3":0.642,"c4":0.4},{"time":0.7667}]},"bone2":{"translate":[{"curve":0.31,"c3":0.645,"c4":0.35},{"time":0.1,"x":36.98,"curve":0.316,"c2":0.23,"c3":0.651,"c4":0.57},{"time":0.1667,"x":-52.39,"curve":0.366,"c2":0.46,"c3":0.754},{"time":0.2333}],"scale":[{"curve":0.305,"c3":0.64,"c4":0.36},{"time":0.1,"x":0.448,"y":0.448,"curve":0.314,"c2":0.24,"c3":0.649,"c4":0.58},{"time":0.1667,"x":1.544,"y":1.544,"curve":0.32,"c2":0.29,"c3":0.757},{"time":0.2333,"curve":0.331,"c3":0.665,"c4":0.33},{"time":0.3,"x":1.023,"y":1.023,"curve":0.307,"c2":0.04,"c3":0.642,"c4":0.4},{"time":0.3667,"x":0.983,"y":0.983,"curve":0.331,"c3":0.665,"c4":0.33},{"time":0.4333,"x":1.035,"y":1.035,"curve":0.307,"c2":0.04,"c3":0.642,"c4":0.4},{"time":0.5,"x":0.983,"y":0.983,"curve":0.331,"c3":0.665,"c4":0.33},{"time":1.6667}]},"bone10":{"scale":[{"x":1.542,"y":1.542}]},"bone4":{"translate":[{"curve":0.292,"c3":0.63,"c4":0.37},{"time":0.2333,"x":27.74,"curve":0.302,"c2":0.22,"c3":0.646,"c4":0.59},{"time":0.3667,"x":27.74,"curve":0.366,"c2":0.46,"c3":0.754},{"time":0.4333}],"scale":[{"curve":0.305,"c3":0.64,"c4":0.36},{"time":0.1,"x":0.448,"y":0.448,"curve":0.314,"c2":0.24,"c3":0.649,"c4":0.58},{"time":0.2333,"x":1.14,"y":1.14,"curve":0.32,"c2":0.29,"c3":0.757},{"time":0.3667,"x":1.578,"y":1.578,"curve":0.32,"c2":0.29,"c3":0.757},{"time":0.4333,"x":1.012,"y":1.012,"curve":0.331,"c3":0.665,"c4":0.33},{"time":0.5,"x":1.023,"y":1.023,"curve":0.307,"c2":0.04,"c3":0.642,"c4":0.4},{"time":0.5667,"x":0.983,"y":0.983,"curve":0.331,"c3":0.665,"c4":0.33},{"time":0.6333,"x":1.023,"y":1.023,"curve":0.307,"c2":0.04,"c3":0.642,"c4":0.4},{"time":0.7,"x":0.983,"y":0.983,"curve":0.331,"c3":0.665,"c4":0.33},{"time":1.6667}]},"bone9":{"scale":[{"x":1.542,"y":1.542}]},"bone3":{"translate":[{"time":0.1667,"curve":0.25,"c3":0.75},{"time":0.2667,"x":-7.01,"curve":0.25,"c3":0.75},{"time":0.3333}],"scale":[{"curve":0.25,"c3":0.75},{"time":0.1,"x":0.448,"y":0.448,"curve":0.25,"c3":0.75},{"time":0.1667,"x":1.14,"y":1.14,"curve":0.25,"c3":0.75},{"time":0.2667,"x":1.541,"y":1.541,"curve":0.25,"c3":0.75},{"time":0.3333,"curve":0.314,"c3":0.648,"c4":0.35},{"time":0.4,"x":1.023,"y":1.023,"curve":0.27,"c2":0.11,"c3":0.639,"c4":0.57},{"time":0.4333,"x":1.014,"y":1.014,"curve":0.378,"c2":0.52,"c3":0.748},{"time":0.4667,"x":0.983,"y":0.983,"curve":0.314,"c3":0.648,"c4":0.35},{"time":0.5333,"x":1.023,"y":1.023,"curve":0.276,"c2":0.11,"c3":0.753},{"time":0.6,"x":0.983,"y":0.983,"curve":0.314,"c3":0.648,"c4":0.35},{"time":1.6667}]},"bone11":{"scale":[{"x":1.381,"y":1.381,"curve":0.25,"c3":0.75},{"time":1.6667,"x":1.524,"y":1.524}]},"bone8":{"scale":[{"x":1.542,"y":1.542}]}},"deform":{"default":{"ban4":{"ban3":[{"curve":0.25,"c3":0.75},{"time":0.1,"offset":1,"vertices":[556.0991,7.0E-5,556.0991,-8.0E-5,-602.4446,-8.0E-5,-602.4446,-8.0E-5,-602.4446,-8.0E-5,-602.4446,7.0E-5,556.0991,7.0E-5,556.0991],"curve":0.25,"c3":0.75},{"time":0.1333}]},"bone7":{"bone7":[{"offset":1,"vertices":[454.37143,0,0,-8.0E-5,-559.93335,-8.0E-5,-559.93335,-8.0E-5,-559.93335,-8.0E-5,-559.93335,-8.0E-5,-559.93335,-8.0E-5,-559.93335,-8.0E-5,-559.93335,-8.0E-5,-559.93335,-8.0E-5,-559.93335,-8.0E-5,-559.93335,-8.0E-5,-559.93335,-8.0E-5,-559.93335,-8.0E-5,-559.93335,-8.0E-5,-559.93335,-8.0E-5,-559.93335,-8.0E-5,-559.93335,-8.0E-5,-559.93335,-8.0E-5,-559.93335,-8.0E-5,-559.93335,-8.0E-5,-559.93335,-8.0E-5,-559.93335,-8.0E-5,-559.93335,6.0E-5,454.37143,6.0E-5,454.37143,6.0E-5,454.37143,6.0E-5,454.37143,6.0E-5,454.37143,6.0E-5,454.37143,6.0E-5,454.37143,6.0E-5,454.37143,6.0E-5,454.37143,6.0E-5,454.37143,6.0E-5,454.37143,6.0E-5,454.37143,6.0E-5,454.37143,6.0E-5,454.37143,6.0E-5,454.37143,6.0E-5,454.37143,6.0E-5,454.37143,6.0E-5,454.37143,6.0E-5,454.37143,6.0E-5,454.37143,6.0E-5,454.37143],"curve":0.25,"c3":0.75},{"time":0.0667,"offset":1,"vertices":[-426.83484,0,0,0,83.74072,0,83.74072,0,83.74072,0,83.74072,0,83.74072,0,83.74072,0,83.74072,0,83.74072,0,83.74072,0,83.74072,0,83.74072,0,83.74072,0,83.74072,0,83.74072,0,83.74072,0,83.74072,0,83.74072,0,83.74072,-2.0E-5,-94.85275,0,83.74072,0,83.74072,0,83.74072,-6.0E-5,-426.83484,-6.0E-5,-426.83484,-6.0E-5,-426.83484,-6.0E-5,-426.83484,-6.0E-5,-426.83484,-6.0E-5,-426.83484,-6.0E-5,-426.83484,-6.0E-5,-426.83484,-6.0E-5,-426.83484,-6.0E-5,-426.83484,-6.0E-5,-426.83484,-6.0E-5,-426.83484,-6.0E-5,-426.83484,-6.0E-5,-426.83484,-6.0E-5,-426.83484,-6.0E-5,-426.83484,-6.0E-5,-426.83484,-6.0E-5,-426.83484,-6.0E-5,-426.83484,-6.0E-5,-426.83484,-6.0E-5,-426.83484],"curve":0.25,"c3":0.75},{"time":0.5,"offset":1,"vertices":[454.37143,0,0,-8.0E-5,-559.93335,-8.0E-5,-559.93335,-8.0E-5,-559.93335,-8.0E-5,-559.93335,-8.0E-5,-559.93335,-8.0E-5,-559.93335,-8.0E-5,-559.93335,-8.0E-5,-559.93335,-8.0E-5,-559.93335,-8.0E-5,-559.93335,-8.0E-5,-559.93335,-8.0E-5,-559.93335,-8.0E-5,-559.93335,-8.0E-5,-559.93335,-8.0E-5,-559.93335,-8.0E-5,-559.93335,-8.0E-5,-559.93335,-8.0E-5,-559.93335,-8.0E-5,-559.93335,-8.0E-5,-559.93335,-8.0E-5,-559.93335,-8.0E-5,-559.93335,6.0E-5,454.37143,6.0E-5,454.37143,6.0E-5,454.37143,6.0E-5,454.37143,6.0E-5,454.37143,6.0E-5,454.37143,6.0E-5,454.37143,6.0E-5,454.37143,6.0E-5,454.37143,6.0E-5,454.37143,6.0E-5,454.37143,6.0E-5,454.37143,6.0E-5,454.37143,6.0E-5,454.37143,6.0E-5,454.37143,6.0E-5,454.37143,6.0E-5,454.37143,6.0E-5,454.37143,6.0E-5,454.37143,6.0E-5,454.37143,6.0E-5,454.37143]}]}}}}}}